deesk/__init__.py
deesk/drivers/__init__.py
deesk/drivers/base.py
deesk/drivers/fs.py
deesk/drivers/memory.py
deesk/drivers/s3.py
deesk/protocols.py
deesk/storage.py
deesk-0.1.0.dist-info/LICENSE
deesk-0.1.0.dist-info/WHEEL
deesk-0.1.0.dist-info/METADATA
deesk-0.1.0.dist-info/RECORD
